hito_nsip/__init__.py
hito_nsip/hito2nsip.cfg.example
hito_nsip/hito2nsip.py
hito_nsip-24.1.1.dist-info/LICENSE
hito_nsip-24.1.1.dist-info/METADATA
hito_nsip-24.1.1.dist-info/WHEEL
hito_nsip-24.1.1.dist-info/entry_points.txt
hito_nsip-24.1.1.dist-info/top_level.txt
hito_nsip-24.1.1.dist-info/RECORD
