Metadata-Version: 2.1
Name: hito_nsip
Version: 24.1.1
Summary: Outils de synchronisation entre Hito et NSIP
Author-email: Michel Jouvin <michel.jouvin@ijclab.in2p3.fr>
License: BSD 3-Clause License
Project-URL: Homepage, https://gitlab.in2p3.fr/hito/hito_nsip
Project-URL: Bug Tracker, https://gitlab.in2p3.fr/hito/hito_nsip/-/issues
Classifier: License :: OSI Approved :: MIT License
Classifier: Operating System :: OS Independent
Classifier: Programming Language :: Python :: 3
Requires-Python: >=3.8
License-File: LICENSE
Requires-Dist: hito-tools >=24.1
